Metadata-Version: 2.1
Name: opencast-camera-control
Version: 0.3.0
Summary: Automated Camera Control for Opencast
Author-email: Lars Kiesow <lkiesow@uos.de>, Jan-Matthis Niermann <janiermann@uos.de>
License:                     GNU GENERAL PUBLIC LICENSE
Project-URL: Homepage, https://github.com/virtUOS/opencast-camera-control
Project-URL: Repository, https://github.com/virtUOS/opencast-camera-control
Requires-Python: >=3.9
License-File: LICENSE
